agentforge/__init__.py
agentforge/agent.py
agentforge/cog.py
agentforge/config.py
agentforge/init_agentforge.py
agentforge/apis/__init__.py
agentforge/apis/anthropic_api.py
agentforge/apis/base_api.py
agentforge/apis/gemini_api.py
agentforge/apis/groq_api.py
agentforge/apis/lm_studio_api.py
agentforge/apis/ollama_api.py
agentforge/apis/openai_api.py
agentforge/apis/openrouter_api.py
agentforge/apis/mixins/__init__.py
agentforge/apis/mixins/audio_input_mixin.py
agentforge/apis/mixins/audio_output_mixin.py
agentforge/apis/mixins/vision_mixin.py
agentforge/config_structs/__init__.py
agentforge/config_structs/agent_config_structs.py
agentforge/config_structs/cog_config_structs.py
agentforge/config_structs/trail_structs.py
agentforge/core/__init__.py
agentforge/core/agent_registry.py
agentforge/core/agent_runner.py
agentforge/core/config_manager.py
agentforge/core/memory_manager.py
agentforge/core/trail_recorder.py
agentforge/core/transition_resolver.py
agentforge/modules/__init__.py
agentforge/modules/actions.py
agentforge/setup_files/__init__.py
agentforge/setup_files/actions/__init__.py
agentforge/setup_files/actions/web_search.yaml
agentforge/setup_files/actions/write_file.yaml
agentforge/setup_files/cogs/__init__.py
agentforge/setup_files/cogs/example_cog.yaml
agentforge/setup_files/cogs/example_cog_all_memories.yaml
agentforge/setup_files/cogs/example_cog_with_chat_memory.yaml
agentforge/setup_files/cogs/example_cog_with_memory.yaml
agentforge/setup_files/cogs/example_cog_with_persona_memory.yaml
agentforge/setup_files/cogs/example_cog_with_scratchpad.yaml
agentforge/setup_files/custom_apis/__init__.py
agentforge/setup_files/personas/__init__.py
agentforge/setup_files/personas/default_assistant.yaml
agentforge/setup_files/prompts/__init__.py
agentforge/setup_files/prompts/response_agent.yaml
agentforge/setup_files/prompts/understand_agent.yaml
agentforge/setup_files/prompts/cog_agents/__init__.py
agentforge/setup_files/prompts/cog_agents/cog_analyze_agent.yaml
agentforge-0.6.4.dist-info/LICENSE
agentforge-0.6.4.dist-info/METADATA
agentforge-0.6.4.dist-info/WHEEL
agentforge-0.6.4.dist-info/entry_points.txt
agentforge-0.6.4.dist-info/top_level.txt
agentforge-0.6.4.dist-info/RECORD
