Metadata-Version: 2.1
Name: agentforge
Version: 0.6.4
Summary: AI-driven task automation system
Home-page: https://github.com/DataBassGit/AgentForge
Author: John Smith, Ansel Anselmi
Author-email: contact@agentforge.net
License: GNU General Public License v3 or later (GPLv3+)
Classifier: Development Status :: 2 - Pre-Alpha
Classifier: Intended Audience :: Developers
Classifier: License :: OSI Approved :: GNU General Public License v3 or later (GPLv3+)
Classifier: Programming Language :: Python :: 3.9
Classifier: Programming Language :: Python :: 3.10
Classifier: Programming Language :: Python :: 3.11
Classifier: Programming Language :: Python :: 3.12
Classifier: Programming Language :: Python :: 3.13
Requires-Python: >=3.9
License-File: LICENSE
Requires-Dist: chromadb >=1.1.0
Requires-Dist: sentence-transformers
Requires-Dist: wheel
Requires-Dist: groq
Requires-Dist: pypdf
Requires-Dist: colorama
Requires-Dist: spacy
Requires-Dist: termcolor ==2.4.0
Requires-Dist: openai
Requires-Dist: anthropic
Requires-Dist: google-api-python-client
Requires-Dist: beautifulsoup4
Requires-Dist: browse
Requires-Dist: scipy
Requires-Dist: discord.py
Requires-Dist: semantic-text-splitter
Requires-Dist: google-generativeai
Requires-Dist: PyYAML
Requires-Dist: ruamel.yaml
Requires-Dist: requests
Requires-Dist: xmltodict
Requires-Dist: setuptools >=70.0.0
Requires-Dist: numpy <2.0.0 ; python_version < "3.12"
Requires-Dist: numpy >=2.0.0 ; python_version >= "3.12"
Provides-Extra: other
Requires-Dist: matplotlib ~=3.9.2 ; extra == 'other'
Requires-Dist: umap ~=0.1.1 ; extra == 'other'
Requires-Dist: cv2 ; extra == 'other'
Requires-Dist: pytesseract ; extra == 'other'
